{
  "playerId": "8474659",
  "season": "20142015",
  "gameType": "playoffs",
  "games": [
    {
      "gameId": 2014030146,
      "gameDate": "2015-04-25",
      "opponent": "WSH",
      "homeRoadFlag": "H",
      "gamesPlayed": 1,
      "assists": 0,
      "goals": 0,
      "points": 0,
      "plusMinus": 0,
      "powerPlayGoals": 0,
      "powerPlayPoints": 0,
      "gameWinningGoals": 0,
      "otGoals": 0,
      "shots": 1,
      "shifts": 19,
      "shorthandedGoals": 0,
      "shorthandedPoints": 0,
      "pim": 10,
      "avgToi": 10.28,
      "avgShots": 1.0,
      "avgShifts": 19.0,
      "gameStats": {
        "assists": 0,
        "goals": 0,
        "points": 0,
        "shots": 1,
        "toi": "10:17",
        "plusMinus": 0
      }
    },
    {
      "gameId": 2014030147,
      "gameDate": "2015-04-27",
      "opponent": "WSH",
      "homeRoadFlag": "R",
      "gamesPlayed": 2,
      "assists": 0,
      "goals": 0,
      "points": 0,
      "plusMinus": 0,
      "powerPlayGoals": 0,
      "powerPlayPoints": 0,
      "gameWinningGoals": 0,
      "otGoals": 0,
      "shots": 1,
      "shifts": 41,
      "shorthandedGoals": 0,
      "shorthandedPoints": 0,
      "pim": 10,
      "avgToi": 11.34,
      "avgShots": 0.5,
      "avgShifts": 20.5,
      "gameStats": {
        "assists": 0,
        "goals": 0,
        "points": 0,
        "shots": 0,
        "toi": "12:24",
        "plusMinus": 0
      }
    }
  ]
}